clip/__init__.py
clip/bpe_simple_vocab_16e6.txt.gz
clip/clip.py
clip/model.py
clip/simple_tokenizer.py
mozuma_clip-1.0.1.data/data/README.md
mozuma_clip-1.0.1.data/data/requirements.txt
mozuma_clip-1.0.1.dist-info/LICENSE
mozuma_clip-1.0.1.dist-info/METADATA
mozuma_clip-1.0.1.dist-info/WHEEL
mozuma_clip-1.0.1.dist-info/top_level.txt
mozuma_clip-1.0.1.dist-info/RECORD
