Metadata-Version: 2.1
Name: mozuma-clip
Version: 1.0.1
Summary: Contrastive Language-Image Pretraining
Home-page: https://github.com/mozuma/CLIP
Author: OpenAI
License: MIT License
Keywords: computer vision,pattern recognition,machine-learning
Classifier: Development Status :: 4 - Beta
Classifier: Environment :: GPU
Classifier: Environment :: GPU :: NVIDIA CUDA
Classifier: Intended Audience :: Developers
Classifier: Intended Audience :: Science/Research
Classifier: License :: OSI Approved :: MIT License
Classifier: Programming Language :: Python
Classifier: Programming Language :: Python :: 3 :: Only
Classifier: Topic :: Multimedia
Classifier: Topic :: Scientific/Engineering :: Artificial Intelligence
Classifier: Topic :: Scientific/Engineering :: Image Recognition
License-File: LICENSE
Requires-Dist: ftfy
Requires-Dist: regex
Requires-Dist: tqdm
Requires-Dist: torch
Requires-Dist: torchvision
Provides-Extra: dev
Requires-Dist: pytest ; extra == 'dev'
